{
  "title": "LA Times, Wed, Jun 14, 2017",
  "subtitle": "",
  "description": "",
  "copyright": "© 2017 Tribune Content Agency, LLC",
  "author": "Agnes Davidson \u0026 C.C. Burnikel / Ed. Rich Norris",
  "authorEmail": "",
  "authorURL": "",
  "help": "",
  "pauseMessage": "",
  "endMessage": "",
  "attributions": "",
  "defaultHintsEnabled": false,
  "hintsEnabled": true,
  "revealEnabled": true,
  "checkEnabled": true,
  "errorCheckModeEnabled": true,
  "srcJPZ": true,
  "showRebus": false,
  "creationTime": 1517907906308,
  "modifiedTime": 1517907906308,
  "publishTime": 1497412800000,
  "publishTimeZone": "Asia/Kolkata",
  "srcFileName": "tca170614.jpz",
  "videoPrerollAds": false,
  "displayAds": false,
  "id": "tca170614",
  "set": "wapo-daily",
  "articleHintsEnabled": true,
  "correctWordPoints": 10,
  "letterPenalty": -1,
  "linkPenalty": -5,
  "bonusPoints": 15,
  "targetTime": 15,
  "clueDisplay": "text",
  "colorFeedbackEnabled": false,
  "allowSharing": true,
  "showHelpMenu": true,
  "hideClueColumns": false,
  "wordLengthsEnabled": false,
  "multiPlayEnabled": false,
  "mediaPreviewEnabled": false,
  "mediaPreviewAndTextEnabled": true,
  "replay": false,
  "startButtonEnabled": false,
  "submitEnabled": false,
  "gatherEmail": false,
  "gatherMobile": false,
  "gatherName": false,
  "locale": "en-US",
  "puzzleType": "CROSSWORD",
  "layoutDiscoveredCommits": 0,
  "layoutDiscoveredMillis": 0,
  "w": 15,
  "h": 15,
  "box": [
    [
      "I",
      "M",
      "O",
      "K",
      "\u0000",
      "O",
      "N",
      "L",
      "I",
      "N",
      "E",
      "\u0000",
      "F",
      "E",
      "D"
    ],
    [
      "P",
      "I",
      "T",
      "A",
      "\u0000",
      "P",
      "A",
      "Y",
      "N",
      "O",
      "W",
      "\u0000",
      "U",
      "S",
      "E"
    ],
    [
      "O",
      "N",
      "T",
      "H",
      "A",
      "T",
      "S",
      "C",
      "O",
      "R",
      "E",
      "\u0000",
      "N",
      "A",
      "B"
    ],
    [
      "S",
      "I",
      "O",
      "U",
      "X",
      "\u0000",
      "\u0000",
      "R",
      "I",
      "M",
      "\u0000",
      "U",
      "N",
      "I",
      "T"
    ],
    [
      "\u0000",
      "\u0000",
      "\u0000",
      "N",
      "E",
      "W",
      "B",
      "A",
      "L",
      "A",
      "N",
      "C",
      "E",
      "\u0000",
      "\u0000"
    ],
    [
      "I",
      "T",
      "S",
      "A",
      "L",
      "I",
      "E",
      "\u0000",
      "\u0000",
      "L",
      "O",
      "L",
      "L",
      "S",
      "\u0000"
    ],
    [
      "R",
      "A",
      "H",
      "S",
      "\u0000",
      "F",
      "I",
      "L",
      "L",
      "\u0000",
      "T",
      "A",
      "C",
      "I",
      "T"
    ],
    [
      "A",
      "C",
      "A",
      "\u0000",
      "B",
      "I",
      "G",
      "T",
      "I",
      "M",
      "E",
      "\u0000",
      "A",
      "L",
      "A"
    ],
    [
      "N",
      "O",
      "M",
      "A",
      "R",
      "\u0000",
      "E",
      "D",
      "N",
      "A",
      "\u0000",
      "S",
      "K",
      "O",
      "R"
    ],
    [
      "\u0000",
      "S",
      "E",
      "R",
      "I",
      "F",
      "\u0000",
      "\u0000",
      "D",
      "N",
      "A",
      "T",
      "E",
      "S",
      "T"
    ],
    [
      "\u0000",
      "\u0000",
      "O",
      "U",
      "T",
      "O",
      "F",
      "S",
      "T",
      "Y",
      "L",
      "E",
      "\u0000",
      "\u0000",
      "\u0000"
    ],
    [
      "P",
      "I",
      "N",
      "G",
      "\u0000",
      "R",
      "E",
      "I",
      "\u0000",
      "\u0000",
      "A",
      "P",
      "P",
      "L",
      "E"
    ],
    [
      "A",
      "N",
      "Y",
      "\u0000",
      "B",
      "O",
      "T",
      "T",
      "O",
      "M",
      "S",
      "H",
      "E",
      "E",
      "T"
    ],
    [
      "U",
      "F",
      "O",
      "\u0000",
      "I",
      "N",
      "C",
      "A",
      "S",
      "E",
      "\u0000",
      "E",
      "R",
      "G",
      "O"
    ],
    [
      "L",
      "O",
      "U",
      "\u0000",
      "T",
      "E",
      "H",
      "R",
      "A",
      "N",
      "\u0000",
      "N",
      "E",
      "O",
      "N"
    ]
  ],
  "clueNums": [
    [
      1,
      13,
      17,
      20,
      0,
      28,
      34,
      38,
      42,
      46,
      50,
      0,
      59,
      64,
      67
    ],
    [
      2,
      0,
      0,
      0,
      0,
      29,
      0,
      0,
      0,
      0,
      0,
      0,
      60,
      0,
      0
    ],
    [
      3,
      0,
      0,
      0,
      23,
      0,
      0,
      0,
      0,
      0,
      0,
      0,
      61,
      0,
      0
    ],
    [
      4,
      0,
      0,
      0,
      0,
      0,
      0,
      39,
      0,
      0,
      0,
      55,
      0,
      0,
      0
    ],
    [
      0,
      0,
      0,
      21,
      0,
      30,
      35,
      0,
      0,
      0,
      51,
      0,
      0,
      0,
      0
    ],
    [
      5,
      14,
      18,
      0,
      0,
      0,
      0,
      0,
      0,
      47,
      0,
      0,
      0,
      65,
      0
    ],
    [
      6,
      0,
      0,
      0,
      0,
      31,
      0,
      40,
      43,
      0,
      52,
      0,
      0,
      0,
      68
    ],
    [
      7,
      0,
      0,
      0,
      24,
      0,
      0,
      0,
      0,
      48,
      0,
      0,
      62,
      0,
      0
    ],
    [
      8,
      0,
      0,
      22,
      0,
      0,
      36,
      0,
      0,
      0,
      0,
      56,
      0,
      0,
      0
    ],
    [
      0,
      15,
      0,
      0,
      0,
      32,
      0,
      0,
      44,
      0,
      53,
      0,
      0,
      0,
      0
    ],
    [
      0,
      0,
      19,
      0,
      0,
      0,
      37,
      41,
      0,
      0,
      0,
      0,
      0,
      0,
      0
    ],
    [
      9,
      16,
      0,
      0,
      0,
      33,
      0,
      0,
      0,
      0,
      54,
      0,
      63,
      66,
      69
    ],
    [
      10,
      0,
      0,
      0,
      25,
      0,
      0,
      0,
      45,
      49,
      0,
      0,
      0,
      0,
      0
    ],
    [
      11,
      0,
      0,
      0,
      26,
      0,
      0,
      0,
      0,
      0,
      0,
      57,
      0,
      0,
      0
    ],
    [
      12,
      0,
      0,
      0,
      27,
      0,
      0,
      0,
      0,
      0,
      0,
      58,
      0,
      0,
      0
    ]
  ],
  "placedWords": [
    {
      "originalTerm": "IPOS",
      "nBoxes": 4,
      "x": 0,
      "y": 0,
      "acrossNotDown": true,
      "clueNum": 1,
      "clue": {
        "date": 0,
        "clue": "Wall St. debuts",
        "fullSentenceLowerCase": ""
      },
      "wordLens": [
        4
      ],
      "intersects": false
    },
    {
      "originalTerm": "IRAN",
      "nBoxes": 4,
      "x": 5,
      "y": 0,
      "acrossNotDown": true,
      "clueNum": 5,
      "clue": {
        "date": 0,
        "clue": "Land formerly ruled by a shah",
        "fullSentenceLowerCase": ""
      },
      "wordLens": [
        4
      ],
      "intersects": false
    },
    {
      "originalTerm": "PAUL",
      "nBoxes": 4,
      "x": 11,
      "y": 0,
      "acrossNotDown": true,
      "clueNum": 9,
      "clue": {
        "date": 0,
        "clue": "Political Ron or Rand",
        "fullSentenceLowerCase": ""
      },
      "wordLens": [
        4
      ],
      "intersects": false
    },
    {
      "originalTerm": "MINI",
      "nBoxes": 4,
      "x": 0,
      "y": 1,
      "acrossNotDown": true,
      "clueNum": 13,
      "clue": {
        "date": 0,
        "clue": "Van starter?",
        "fullSentenceLowerCase": ""
      },
      "wordLens": [
        4
      ],
      "intersects": false
    },
    {
      "originalTerm": "TACOS",
      "nBoxes": 5,
      "x": 5,
      "y": 1,
      "acrossNotDown": true,
      "clueNum": 14,
      "clue": {
        "date": 0,
        "clue": "Stuffed shells",
        "fullSentenceLowerCase": ""
      },
      "wordLens": [
        5
      ],
      "intersects": false
    },
    {
      "originalTerm": "INFO",
      "nBoxes": 4,
      "x": 11,
      "y": 1,
      "acrossNotDown": true,
      "clueNum": 16,
      "clue": {
        "date": 0,
        "clue": "Data, for instance",
        "fullSentenceLowerCase": ""
      },
      "wordLens": [
        4
      ],
      "intersects": false
    },
    {
      "originalTerm": "OTTO",
      "nBoxes": 4,
      "x": 0,
      "y": 2,
      "acrossNotDown": true,
      "clueNum": 17,
      "clue": {
        "date": 0,
        "clue": "\"Big __\" Delaney: \"Sons of Anarchy\" character",
        "fullSentenceLowerCase": ""
      },
      "wordLens": [
        4
      ],
      "intersects": false
    },
    {
      "originalTerm": "SHAMEONYOU",
      "nBoxes": 10,
      "x": 5,
      "y": 2,
      "acrossNotDown": true,
      "clueNum": 18,
      "clue": {
        "date": 0,
        "clue": "\"Tsk tsk\"",
        "fullSentenceLowerCase": ""
      },
      "wordLens": [
        10
      ],
      "intersects": false
    },
    {
      "originalTerm": "KAHUNAS",
      "nBoxes": 7,
      "x": 0,
      "y": 3,
      "acrossNotDown": true,
      "clueNum": 20,
      "clue": {
        "date": 0,
        "clue": "Hawaiian priests",
        "fullSentenceLowerCase": ""
      },
      "wordLens": [
        7
      ],
      "intersects": false
    },
    {
      "originalTerm": "ARUG",
      "nBoxes": 4,
      "x": 8,
      "y": 3,
      "acrossNotDown": true,
      "clueNum": 22,
      "clue": {
        "date": 0,
        "clue": "\" ... bug in __\"",
        "fullSentenceLowerCase": ""
      },
      "wordLens": [
        4
      ],
      "intersects": false
    },
    {
      "originalTerm": "AXEL",
      "nBoxes": 4,
      "x": 2,
      "y": 4,
      "acrossNotDown": true,
      "clueNum": 23,
      "clue": {
        "date": 0,
        "clue": "Skating jump",
        "fullSentenceLowerCase": ""
      },
      "wordLens": [
        4
      ],
      "intersects": false
    },
    {
      "originalTerm": "BRIT",
      "nBoxes": 4,
      "x": 7,
      "y": 4,
      "acrossNotDown": true,
      "clueNum": 24,
      "clue": {
        "date": 0,
        "clue": "Petrol pumper",
        "fullSentenceLowerCase": ""
      },
      "wordLens": [
        4
      ],
      "intersects": false
    },
    {
      "originalTerm": "BIT",
      "nBoxes": 3,
      "x": 12,
      "y": 4,
      "acrossNotDown": true,
      "clueNum": 25,
      "clue": {
        "date": 0,
        "clue": "Went for the lure",
        "fullSentenceLowerCase": ""
      },
      "wordLens": [
        3
      ],
      "intersects": false
    },
    {
      "originalTerm": "OPT",
      "nBoxes": 3,
      "x": 0,
      "y": 5,
      "acrossNotDown": true,
      "clueNum": 28,
      "clue": {
        "date": 0,
        "clue": "Decide",
        "fullSentenceLowerCase": ""
      },
      "wordLens": [
        3
      ],
      "intersects": false
    },
    {
      "originalTerm": "WIFI",
      "nBoxes": 4,
      "x": 4,
      "y": 5,
      "acrossNotDown": true,
      "clueNum": 30,
      "clue": {
        "date": 0,
        "clue": "Starbucks amenity",
        "fullSentenceLowerCase": ""
      },
      "wordLens": [
        4
      ],
      "intersects": false
    },
    {
      "originalTerm": "FORONE",
      "nBoxes": 6,
      "x": 9,
      "y": 5,
      "acrossNotDown": true,
      "clueNum": 32,
      "clue": {
        "date": 0,
        "clue": "As an example",
        "fullSentenceLowerCase": ""
      },
      "wordLens": [
        6
      ],
      "intersects": false
    },
    {
      "originalTerm": "NAS",
      "nBoxes": 3,
      "x": 0,
      "y": 6,
      "acrossNotDown": true,
      "clueNum": 34,
      "clue": {
        "date": 0,
        "clue": "\"Street Dreams\" rapper",
        "fullSentenceLowerCase": ""
      },
      "wordLens": [
        3
      ],
      "intersects": false
    },
    {
      "originalTerm": "BEIGE",
      "nBoxes": 5,
      "x": 4,
      "y": 6,
      "acrossNotDown": true,
      "clueNum": 35,
      "clue": {
        "date": 0,
        "clue": "Hosiery hue",
        "fullSentenceLowerCase": ""
      },
      "wordLens": [
        5
      ],
      "intersects": false
    },
    {
      "originalTerm": "FETCH",
      "nBoxes": 5,
      "x": 10,
      "y": 6,
      "acrossNotDown": true,
      "clueNum": 37,
      "clue": {
        "date": 0,
        "clue": "Get",
        "fullSentenceLowerCase": ""
      },
      "wordLens": [
        5
      ],
      "intersects": false
    },
    {
      "originalTerm": "LYCRA",
      "nBoxes": 5,
      "x": 0,
      "y": 7,
      "acrossNotDown": true,
      "clueNum": 38,
      "clue": {
        "date": 0,
        "clue": "Stretchy synthetic",
        "fullSentenceLowerCase": ""
      },
      "wordLens": [
        5
      ],
      "intersects": false
    },
    {
      "originalTerm": "LTD",
      "nBoxes": 3,
      "x": 6,
      "y": 7,
      "acrossNotDown": true,
      "clueNum": 40,
      "clue": {
        "date": 0,
        "clue": "Inc. relative",
        "fullSentenceLowerCase": ""
      },
      "wordLens": [
        3
      ],
      "intersects": false
    },
    {
      "originalTerm": "SITAR",
      "nBoxes": 5,
      "x": 10,
      "y": 7,
      "acrossNotDown": true,
      "clueNum": 41,
      "clue": {
        "date": 0,
        "clue": "Ravi Shankar\u0027s instrument",
        "fullSentenceLowerCase": ""
      },
      "wordLens": [
        5
      ],
      "intersects": false
    },
    {
      "originalTerm": "INOIL",
      "nBoxes": 5,
      "x": 0,
      "y": 8,
      "acrossNotDown": true,
      "clueNum": 42,
      "clue": {
        "date": 0,
        "clue": "How some tuna is packed",
        "fullSentenceLowerCase": ""
      },
      "wordLens": [
        5
      ],
      "intersects": false
    },
    {
      "originalTerm": "LINDT",
      "nBoxes": 5,
      "x": 6,
      "y": 8,
      "acrossNotDown": true,
      "clueNum": 43,
      "clue": {
        "date": 0,
        "clue": "Swiss chocolatier since 1845",
        "fullSentenceLowerCase": ""
      },
      "wordLens": [
        5
      ],
      "intersects": false
    },
    {
      "originalTerm": "OSA",
      "nBoxes": 3,
      "x": 12,
      "y": 8,
      "acrossNotDown": true,
      "clueNum": 45,
      "clue": {
        "date": 0,
        "clue": "Mama bear, in Tabasco",
        "fullSentenceLowerCase": ""
      },
      "wordLens": [
        3
      ],
      "intersects": false
    },
    {
      "originalTerm": "NORMAL",
      "nBoxes": 6,
      "x": 0,
      "y": 9,
      "acrossNotDown": true,
      "clueNum": 46,
      "clue": {
        "date": 0,
        "clue": "Standard",
        "fullSentenceLowerCase": ""
      },
      "wordLens": [
        6
      ],
      "intersects": false
    },
    {
      "originalTerm": "MANY",
      "nBoxes": 4,
      "x": 7,
      "y": 9,
      "acrossNotDown": true,
      "clueNum": 48,
      "clue": {
        "date": 0,
        "clue": "More than a few",
        "fullSentenceLowerCase": ""
      },
      "wordLens": [
        4
      ],
      "intersects": false
    },
    {
      "originalTerm": "MEN",
      "nBoxes": 3,
      "x": 12,
      "y": 9,
      "acrossNotDown": true,
      "clueNum": 49,
      "clue": {
        "date": 0,
        "clue": "Bishops and knights",
        "fullSentenceLowerCase": ""
      },
      "wordLens": [
        3
      ],
      "intersects": false
    },
    {
      "originalTerm": "EWE",
      "nBoxes": 3,
      "x": 0,
      "y": 10,
      "acrossNotDown": true,
      "clueNum": 50,
      "clue": {
        "date": 0,
        "clue": "Animal common in rebus puzzles",
        "fullSentenceLowerCase": ""
      },
      "wordLens": [
        3
      ],
      "intersects": false
    },
    {
      "originalTerm": "NOTE",
      "nBoxes": 4,
      "x": 4,
      "y": 10,
      "acrossNotDown": true,
      "clueNum": 51,
      "clue": {
        "date": 0,
        "clue": "Permission slip",
        "fullSentenceLowerCase": ""
      },
      "wordLens": [
        4
      ],
      "intersects": false
    },
    {
      "originalTerm": "ALAS",
      "nBoxes": 4,
      "x": 9,
      "y": 10,
      "acrossNotDown": true,
      "clueNum": 53,
      "clue": {
        "date": 0,
        "clue": "\"Too bad\"",
        "fullSentenceLowerCase": ""
      },
      "wordLens": [
        4
      ],
      "intersects": false
    },
    {
      "originalTerm": "UCLA",
      "nBoxes": 4,
      "x": 3,
      "y": 11,
      "acrossNotDown": true,
      "clueNum": 55,
      "clue": {
        "date": 0,
        "clue": "Pac-12 team",
        "fullSentenceLowerCase": ""
      },
      "wordLens": [
        4
      ],
      "intersects": false
    },
    {
      "originalTerm": "STEPHEN",
      "nBoxes": 7,
      "x": 8,
      "y": 11,
      "acrossNotDown": true,
      "clueNum": 56,
      "clue": {
        "date": 0,
        "clue": "King of fiction",
        "fullSentenceLowerCase": ""
      },
      "wordLens": [
        7
      ],
      "intersects": false
    },
    {
      "originalTerm": "FUNNELCAKE",
      "nBoxes": 10,
      "x": 0,
      "y": 12,
      "acrossNotDown": true,
      "clueNum": 59,
      "clue": {
        "date": 0,
        "clue": "Deep-fried carnival confection",
        "fullSentenceLowerCase": ""
      },
      "wordLens": [
        10
      ],
      "intersects": false
    },
    {
      "originalTerm": "PERE",
      "nBoxes": 4,
      "x": 11,
      "y": 12,
      "acrossNotDown": true,
      "clueNum": 63,
      "clue": {
        "date": 0,
        "clue": "Dad, to Dumas",
        "fullSentenceLowerCase": ""
      },
      "wordLens": [
        4
      ],
      "intersects": false
    },
    {
      "originalTerm": "ESAI",
      "nBoxes": 4,
      "x": 0,
      "y": 13,
      "acrossNotDown": true,
      "clueNum": 64,
      "clue": {
        "date": 0,
        "clue": "Morales of \"The Brink\"",
        "fullSentenceLowerCase": ""
      },
      "wordLens": [
        4
      ],
      "intersects": false
    },
    {
      "originalTerm": "SILOS",
      "nBoxes": 5,
      "x": 5,
      "y": 13,
      "acrossNotDown": true,
      "clueNum": 65,
      "clue": {
        "date": 0,
        "clue": "Corn Belt towers",
        "fullSentenceLowerCase": ""
      },
      "wordLens": [
        5
      ],
      "intersects": false
    },
    {
      "originalTerm": "LEGO",
      "nBoxes": 4,
      "x": 11,
      "y": 13,
      "acrossNotDown": true,
      "clueNum": 66,
      "clue": {
        "date": 0,
        "clue": "Toy brand with a Ninjago line",
        "fullSentenceLowerCase": ""
      },
      "wordLens": [
        4
      ],
      "intersects": false
    },
    {
      "originalTerm": "DEBT",
      "nBoxes": 4,
      "x": 0,
      "y": 14,
      "acrossNotDown": true,
      "clueNum": 67,
      "clue": {
        "date": 0,
        "clue": "It\u0027s outstanding",
        "fullSentenceLowerCase": ""
      },
      "wordLens": [
        4
      ],
      "intersects": false
    },
    {
      "originalTerm": "TART",
      "nBoxes": 4,
      "x": 6,
      "y": 14,
      "acrossNotDown": true,
      "clueNum": 68,
      "clue": {
        "date": 0,
        "clue": "Small pie",
        "fullSentenceLowerCase": ""
      },
      "wordLens": [
        4
      ],
      "intersects": false
    },
    {
      "originalTerm": "ETON",
      "nBoxes": 4,
      "x": 11,
      "y": 14,
      "acrossNotDown": true,
      "clueNum": 69,
      "clue": {
        "date": 0,
        "clue": "Thames school",
        "fullSentenceLowerCase": ""
      },
      "wordLens": [
        4
      ],
      "intersects": false
    },
    {
      "originalTerm": "IMOK",
      "nBoxes": 4,
      "x": 0,
      "y": 0,
      "acrossNotDown": false,
      "clueNum": 1,
      "clue": {
        "date": 0,
        "clue": "\"No harm done\"",
        "fullSentenceLowerCase": ""
      },
      "wordLens": [
        4
      ],
      "intersects": false
    },
    {
      "originalTerm": "PITA",
      "nBoxes": 4,
      "x": 1,
      "y": 0,
      "acrossNotDown": false,
      "clueNum": 2,
      "clue": {
        "date": 0,
        "clue": "Baba ghanouj bread",
        "fullSentenceLowerCase": ""
      },
      "wordLens": [
        4
      ],
      "intersects": false
    },
    {
      "originalTerm": "ONTHATSCORE",
      "nBoxes": 11,
      "x": 2,
      "y": 0,
      "acrossNotDown": false,
      "clueNum": 3,
      "clue": {
        "date": 0,
        "clue": "*\"Regarding the subject at hand ... \"",
        "fullSentenceLowerCase": ""
      },
      "wordLens": [
        11
      ],
      "intersects": false
    },
    {
      "originalTerm": "SIOUX",
      "nBoxes": 5,
      "x": 3,
      "y": 0,
      "acrossNotDown": false,
      "clueNum": 4,
      "clue": {
        "date": 0,
        "clue": "Iowa\u0027s __ City",
        "fullSentenceLowerCase": ""
      },
      "wordLens": [
        5
      ],
      "intersects": false
    },
    {
      "originalTerm": "ITSALIE",
      "nBoxes": 7,
      "x": 5,
      "y": 0,
      "acrossNotDown": false,
      "clueNum": 5,
      "clue": {
        "date": 0,
        "clue": "\"So not true!\"",
        "fullSentenceLowerCase": ""
      },
      "wordLens": [
        7
      ],
      "intersects": false
    },
    {
      "originalTerm": "RAHS",
      "nBoxes": 4,
      "x": 6,
      "y": 0,
      "acrossNotDown": false,
      "clueNum": 6,
      "clue": {
        "date": 0,
        "clue": "Cheers from tiers",
        "fullSentenceLowerCase": ""
      },
      "wordLens": [
        4
      ],
      "intersects": false
    },
    {
      "originalTerm": "ACA",
      "nBoxes": 3,
      "x": 7,
      "y": 0,
      "acrossNotDown": false,
      "clueNum": 7,
      "clue": {
        "date": 0,
        "clue": "Obamacare, briefly",
        "fullSentenceLowerCase": ""
      },
      "wordLens": [
        3
      ],
      "intersects": false
    },
    {
      "originalTerm": "NOMAR",
      "nBoxes": 5,
      "x": 8,
      "y": 0,
      "acrossNotDown": false,
      "clueNum": 8,
      "clue": {
        "date": 0,
        "clue": "Baseball analyst Garciaparra",
        "fullSentenceLowerCase": ""
      },
      "wordLens": [
        5
      ],
      "intersects": false
    },
    {
      "originalTerm": "PING",
      "nBoxes": 4,
      "x": 11,
      "y": 0,
      "acrossNotDown": false,
      "clueNum": 9,
      "clue": {
        "date": 0,
        "clue": "\"And the Putter Went ... __\": golf history book",
        "fullSentenceLowerCase": ""
      },
      "wordLens": [
        4
      ],
      "intersects": false
    },
    {
      "originalTerm": "ANY",
      "nBoxes": 3,
      "x": 12,
      "y": 0,
      "acrossNotDown": false,
      "clueNum": 10,
      "clue": {
        "date": 0,
        "clue": "\"__ questions?\"",
        "fullSentenceLowerCase": ""
      },
      "wordLens": [
        3
      ],
      "intersects": false
    },
    {
      "originalTerm": "UFO",
      "nBoxes": 3,
      "x": 13,
      "y": 0,
      "acrossNotDown": false,
      "clueNum": 11,
      "clue": {
        "date": 0,
        "clue": "Blur in a tabloid pic",
        "fullSentenceLowerCase": ""
      },
      "wordLens": [
        3
      ],
      "intersects": false
    },
    {
      "originalTerm": "LOU",
      "nBoxes": 3,
      "x": 14,
      "y": 0,
      "acrossNotDown": false,
      "clueNum": 12,
      "clue": {
        "date": 0,
        "clue": "Fox Business anchor Dobbs",
        "fullSentenceLowerCase": ""
      },
      "wordLens": [
        3
      ],
      "intersects": false
    },
    {
      "originalTerm": "SERIF",
      "nBoxes": 5,
      "x": 9,
      "y": 1,
      "acrossNotDown": false,
      "clueNum": 15,
      "clue": {
        "date": 0,
        "clue": "Letter flourish",
        "fullSentenceLowerCase": ""
      },
      "wordLens": [
        5
      ],
      "intersects": false
    },
    {
      "originalTerm": "OUTOFSTYLE",
      "nBoxes": 10,
      "x": 10,
      "y": 2,
      "acrossNotDown": false,
      "clueNum": 19,
      "clue": {
        "date": 0,
        "clue": "*Like leisure suits and Nehru jackets",
        "fullSentenceLowerCase": ""
      },
      "wordLens": [
        10
      ],
      "intersects": false
    },
    {
      "originalTerm": "NEWBALANCE",
      "nBoxes": 10,
      "x": 4,
      "y": 3,
      "acrossNotDown": false,
      "clueNum": 21,
      "clue": {
        "date": 0,
        "clue": "*Nike competitor",
        "fullSentenceLowerCase": ""
      },
      "wordLens": [
        10
      ],
      "intersects": false
    },
    {
      "originalTerm": "BIGTIME",
      "nBoxes": 7,
      "x": 7,
      "y": 4,
      "acrossNotDown": false,
      "clueNum": 24,
      "clue": {
        "date": 0,
        "clue": "*Major-league",
        "fullSentenceLowerCase": ""
      },
      "wordLens": [
        7
      ],
      "intersects": false
    },
    {
      "originalTerm": "BOTTOMSHEET",
      "nBoxes": 11,
      "x": 12,
      "y": 4,
      "acrossNotDown": false,
      "clueNum": 25,
      "clue": {
        "date": 0,
        "clue": "Bed cover ... or, literally, what the end of each answer to a starred clue is",
        "fullSentenceLowerCase": ""
      },
      "wordLens": [
        11
      ],
      "intersects": false
    },
    {
      "originalTerm": "INCASE",
      "nBoxes": 6,
      "x": 13,
      "y": 4,
      "acrossNotDown": false,
      "clueNum": 26,
      "clue": {
        "date": 0,
        "clue": "As a precaution",
        "fullSentenceLowerCase": ""
      },
      "wordLens": [
        6
      ],
      "intersects": false
    },
    {
      "originalTerm": "TEHRAN",
      "nBoxes": 6,
      "x": 14,
      "y": 4,
      "acrossNotDown": false,
      "clueNum": 27,
      "clue": {
        "date": 0,
        "clue": "5-Across capital",
        "fullSentenceLowerCase": ""
      },
      "wordLens": [
        6
      ],
      "intersects": false
    },
    {
      "originalTerm": "ONLINE",
      "nBoxes": 6,
      "x": 0,
      "y": 5,
      "acrossNotDown": false,
      "clueNum": 28,
      "clue": {
        "date": 0,
        "clue": "How much shopping is done",
        "fullSentenceLowerCase": ""
      },
      "wordLens": [
        6
      ],
      "intersects": false
    },
    {
      "originalTerm": "PAYNOW",
      "nBoxes": 6,
      "x": 1,
      "y": 5,
      "acrossNotDown": false,
      "clueNum": 29,
      "clue": {
        "date": 0,
        "clue": "Webpage option under an invoice",
        "fullSentenceLowerCase": ""
      },
      "wordLens": [
        6
      ],
      "intersects": false
    },
    {
      "originalTerm": "FILL",
      "nBoxes": 4,
      "x": 6,
      "y": 5,
      "acrossNotDown": false,
      "clueNum": 31,
      "clue": {
        "date": 0,
        "clue": "Top off, say",
        "fullSentenceLowerCase": ""
      },
      "wordLens": [
        4
      ],
      "intersects": false
    },
    {
      "originalTerm": "REI",
      "nBoxes": 3,
      "x": 11,
      "y": 5,
      "acrossNotDown": false,
      "clueNum": 33,
      "clue": {
        "date": 0,
        "clue": "Retailer that abstained from Black Friday in 2015 and launched an #OptOutside movement instead",
        "fullSentenceLowerCase": ""
      },
      "wordLens": [
        3
      ],
      "intersects": false
    },
    {
      "originalTerm": "EDNA",
      "nBoxes": 4,
      "x": 8,
      "y": 6,
      "acrossNotDown": false,
      "clueNum": 36,
      "clue": {
        "date": 0,
        "clue": "Flamboyant Dame",
        "fullSentenceLowerCase": ""
      },
      "wordLens": [
        4
      ],
      "intersects": false
    },
    {
      "originalTerm": "RIM",
      "nBoxes": 3,
      "x": 3,
      "y": 7,
      "acrossNotDown": false,
      "clueNum": 39,
      "clue": {
        "date": 0,
        "clue": "Cup lip",
        "fullSentenceLowerCase": ""
      },
      "wordLens": [
        3
      ],
      "intersects": false
    },
    {
      "originalTerm": "DNATEST",
      "nBoxes": 7,
      "x": 9,
      "y": 8,
      "acrossNotDown": false,
      "clueNum": 44,
      "clue": {
        "date": 0,
        "clue": "Crime lab procedure",
        "fullSentenceLowerCase": ""
      },
      "wordLens": [
        7
      ],
      "intersects": false
    },
    {
      "originalTerm": "LOLLS",
      "nBoxes": 5,
      "x": 5,
      "y": 9,
      "acrossNotDown": false,
      "clueNum": 47,
      "clue": {
        "date": 0,
        "clue": "Sprawls on the couch",
        "fullSentenceLowerCase": ""
      },
      "wordLens": [
        5
      ],
      "intersects": false
    },
    {
      "originalTerm": "TACIT",
      "nBoxes": 5,
      "x": 6,
      "y": 10,
      "acrossNotDown": false,
      "clueNum": 52,
      "clue": {
        "date": 0,
        "clue": "Implied",
        "fullSentenceLowerCase": ""
      },
      "wordLens": [
        5
      ],
      "intersects": false
    },
    {
      "originalTerm": "APPLE",
      "nBoxes": 5,
      "x": 11,
      "y": 10,
      "acrossNotDown": false,
      "clueNum": 54,
      "clue": {
        "date": 0,
        "clue": "Cobbler fruit",
        "fullSentenceLowerCase": ""
      },
      "wordLens": [
        5
      ],
      "intersects": false
    },
    {
      "originalTerm": "UNIT",
      "nBoxes": 4,
      "x": 3,
      "y": 11,
      "acrossNotDown": false,
      "clueNum": 55,
      "clue": {
        "date": 0,
        "clue": "Foot or furlong",
        "fullSentenceLowerCase": ""
      },
      "wordLens": [
        4
      ],
      "intersects": false
    },
    {
      "originalTerm": "SKOR",
      "nBoxes": 4,
      "x": 8,
      "y": 11,
      "acrossNotDown": false,
      "clueNum": 56,
      "clue": {
        "date": 0,
        "clue": "Hershey\u0027s toffee bar",
        "fullSentenceLowerCase": ""
      },
      "wordLens": [
        4
      ],
      "intersects": false
    },
    {
      "originalTerm": "ERGO",
      "nBoxes": 4,
      "x": 13,
      "y": 11,
      "acrossNotDown": false,
      "clueNum": 57,
      "clue": {
        "date": 0,
        "clue": "Thus",
        "fullSentenceLowerCase": ""
      },
      "wordLens": [
        4
      ],
      "intersects": false
    },
    {
      "originalTerm": "NEON",
      "nBoxes": 4,
      "x": 14,
      "y": 11,
      "acrossNotDown": false,
      "clueNum": 58,
      "clue": {
        "date": 0,
        "clue": "Flashy light",
        "fullSentenceLowerCase": ""
      },
      "wordLens": [
        4
      ],
      "intersects": false
    },
    {
      "originalTerm": "FED",
      "nBoxes": 3,
      "x": 0,
      "y": 12,
      "acrossNotDown": false,
      "clueNum": 59,
      "clue": {
        "date": 0,
        "clue": "Served dinner to",
        "fullSentenceLowerCase": ""
      },
      "wordLens": [
        3
      ],
      "intersects": false
    },
    {
      "originalTerm": "USE",
      "nBoxes": 3,
      "x": 1,
      "y": 12,
      "acrossNotDown": false,
      "clueNum": 60,
      "clue": {
        "date": 0,
        "clue": "Take advantage of",
        "fullSentenceLowerCase": ""
      },
      "wordLens": [
        3
      ],
      "intersects": false
    },
    {
      "originalTerm": "NAB",
      "nBoxes": 3,
      "x": 2,
      "y": 12,
      "acrossNotDown": false,
      "clueNum": 61,
      "clue": {
        "date": 0,
        "clue": "Arrest",
        "fullSentenceLowerCase": ""
      },
      "wordLens": [
        3
      ],
      "intersects": false
    },
    {
      "originalTerm": "ALA",
      "nBoxes": 3,
      "x": 7,
      "y": 12,
      "acrossNotDown": false,
      "clueNum": 62,
      "clue": {
        "date": 0,
        "clue": "Menu catchphrase",
        "fullSentenceLowerCase": ""
      },
      "wordLens": [
        3
      ],
      "intersects": false
    }
  ],
  "boxToPlacedWordsIdxs": [
    [
      [
        0,
        41
      ],
      [
        3,
        41
      ],
      [
        6,
        41
      ],
      [
        8,
        41
      ],
      null,
      [
        13,
        60
      ],
      [
        16,
        60
      ],
      [
        19,
        60
      ],
      [
        22,
        60
      ],
      [
        25,
        60
      ],
      [
        28,
        60
      ],
      null,
      [
        33,
        74
      ],
      [
        35,
        74
      ],
      [
        38,
        74
      ]
    ],
    [
      [
        42,
        0
      ],
      [
        3,
        42
      ],
      [
        6,
        42
      ],
      [
        8,
        42
      ],
      null,
      [
        61,
        13
      ],
      [
        16,
        61
      ],
      [
        19,
        61
      ],
      [
        22,
        61
      ],
      [
        25,
        61
      ],
      [
        28,
        61
      ],
      null,
      [
        75,
        33
      ],
      [
        35,
        75
      ],
      [
        38,
        75
      ]
    ],
    [
      [
        43,
        0
      ],
      [
        3,
        43
      ],
      [
        6,
        43
      ],
      [
        8,
        43
      ],
      [
        10,
        43
      ],
      [
        13,
        43
      ],
      [
        16,
        43
      ],
      [
        19,
        43
      ],
      [
        22,
        43
      ],
      [
        25,
        43
      ],
      [
        28,
        43
      ],
      null,
      [
        76,
        33
      ],
      [
        35,
        76
      ],
      [
        38,
        76
      ]
    ],
    [
      [
        44,
        0
      ],
      [
        3,
        44
      ],
      [
        6,
        44
      ],
      [
        8,
        44
      ],
      [
        10,
        44
      ],
      null,
      null,
      [
        65,
        19
      ],
      [
        22,
        65
      ],
      [
        25,
        65
      ],
      null,
      [
        31,
        70
      ],
      [
        33,
        70
      ],
      [
        35,
        70
      ],
      [
        38,
        70
      ]
    ],
    [
      null,
      null,
      null,
      [
        55,
        8
      ],
      [
        10,
        55
      ],
      [
        14,
        55
      ],
      [
        17,
        55
      ],
      [
        19,
        55
      ],
      [
        22,
        55
      ],
      [
        25,
        55
      ],
      [
        29,
        55
      ],
      [
        31,
        55
      ],
      [
        33,
        55
      ],
      null,
      null
    ],
    [
      [
        1,
        45
      ],
      [
        4,
        45
      ],
      [
        7,
        45
      ],
      [
        8,
        45
      ],
      [
        10,
        45
      ],
      [
        14,
        45
      ],
      [
        17,
        45
      ],
      null,
      null,
      [
        67,
        25
      ],
      [
        29,
        67
      ],
      [
        31,
        67
      ],
      [
        33,
        67
      ],
      [
        36,
        67
      ],
      null
    ],
    [
      [
        46,
        1
      ],
      [
        4,
        46
      ],
      [
        7,
        46
      ],
      [
        8,
        46
      ],
      null,
      [
        62,
        14
      ],
      [
        17,
        62
      ],
      [
        20,
        62
      ],
      [
        23,
        62
      ],
      null,
      [
        68,
        29
      ],
      [
        31,
        68
      ],
      [
        33,
        68
      ],
      [
        36,
        68
      ],
      [
        39,
        68
      ]
    ],
    [
      [
        47,
        1
      ],
      [
        4,
        47
      ],
      [
        7,
        47
      ],
      null,
      [
        11,
        56
      ],
      [
        14,
        56
      ],
      [
        17,
        56
      ],
      [
        20,
        56
      ],
      [
        23,
        56
      ],
      [
        26,
        56
      ],
      [
        29,
        56
      ],
      null,
      [
        77,
        33
      ],
      [
        36,
        77
      ],
      [
        39,
        77
      ]
    ],
    [
      [
        48,
        1
      ],
      [
        4,
        48
      ],
      [
        7,
        48
      ],
      [
        9,
        48
      ],
      [
        11,
        48
      ],
      null,
      [
        64,
        17
      ],
      [
        20,
        64
      ],
      [
        23,
        64
      ],
      [
        26,
        64
      ],
      null,
      [
        32,
        71
      ],
      [
        33,
        71
      ],
      [
        36,
        71
      ],
      [
        39,
        71
      ]
    ],
    [
      null,
      [
        53,
        4
      ],
      [
        7,
        53
      ],
      [
        9,
        53
      ],
      [
        11,
        53
      ],
      [
        15,
        53
      ],
      null,
      null,
      [
        66,
        23
      ],
      [
        26,
        66
      ],
      [
        30,
        66
      ],
      [
        32,
        66
      ],
      [
        33,
        66
      ],
      [
        36,
        66
      ],
      [
        39,
        66
      ]
    ],
    [
      null,
      null,
      [
        54,
        7
      ],
      [
        9,
        54
      ],
      [
        11,
        54
      ],
      [
        15,
        54
      ],
      [
        18,
        54
      ],
      [
        21,
        54
      ],
      [
        23,
        54
      ],
      [
        26,
        54
      ],
      [
        30,
        54
      ],
      [
        32,
        54
      ],
      null,
      null,
      null
    ],
    [
      [
        2,
        49
      ],
      [
        5,
        49
      ],
      [
        7,
        49
      ],
      [
        9,
        49
      ],
      null,
      [
        63,
        15
      ],
      [
        18,
        63
      ],
      [
        21,
        63
      ],
      null,
      null,
      [
        69,
        30
      ],
      [
        32,
        69
      ],
      [
        34,
        69
      ],
      [
        37,
        69
      ],
      [
        40,
        69
      ]
    ],
    [
      [
        50,
        2
      ],
      [
        5,
        50
      ],
      [
        7,
        50
      ],
      null,
      [
        12,
        57
      ],
      [
        15,
        57
      ],
      [
        18,
        57
      ],
      [
        21,
        57
      ],
      [
        24,
        57
      ],
      [
        27,
        57
      ],
      [
        30,
        57
      ],
      [
        32,
        57
      ],
      [
        34,
        57
      ],
      [
        37,
        57
      ],
      [
        40,
        57
      ]
    ],
    [
      [
        51,
        2
      ],
      [
        5,
        51
      ],
      [
        7,
        51
      ],
      null,
      [
        58,
        12
      ],
      [
        15,
        58
      ],
      [
        18,
        58
      ],
      [
        21,
        58
      ],
      [
        24,
        58
      ],
      [
        27,
        58
      ],
      null,
      [
        72,
        32
      ],
      [
        34,
        72
      ],
      [
        37,
        72
      ],
      [
        40,
        72
      ]
    ],
    [
      [
        52,
        2
      ],
      [
        5,
        52
      ],
      [
        7,
        52
      ],
      null,
      [
        59,
        12
      ],
      [
        15,
        59
      ],
      [
        18,
        59
      ],
      [
        21,
        59
      ],
      [
        24,
        59
      ],
      [
        27,
        59
      ],
      null,
      [
        73,
        32
      ],
      [
        34,
        73
      ],
      [
        37,
        73
      ],
      [
        40,
        73
      ]
    ]
  ],
  "tags": [
    "tca"
  ],
  "level": 0,
  "levelsExhausted": true,
  "haveMessages": true,
  "placeAll": false,
  "caseSensitive": false
}
