{"title":"LA Times, Sat, Sep 23, 2017","description":"","copyright":
  "© 2017 Tribune Content Agency, LLC","author":
  "Mark Diehl / Ed. Rich Norris","help":" ","authorEmail":"","authorURL":
  "","endMessage":"","attributions":"","defaultHintsEnabled":false,
  "hintsEnabled":true,"revealEnabled":true,"checkEnabled":true,
  "errorCheckModeEnabled":true,"srcJPZ":true,"showRebus":false,
  "rebusPresent":false,"creationTime":1503601549722,"publishTime":
  1506139200000,"srcFileName":"tca170923.jpz","videoPrerollAds":false,
  "displayAds":false,"id":"tca170923","set":"wapo-daily",
  "articleHintsEnabled":true,"correctWordPoints":10,"letterPenalty":-1,
  "linkPenalty":-5,"bonusPoints":15,"targetTime":15,"clueDisplay":"text",
  "colorFeedbackEnabled":false,"allowSharing":true,"showHelpMenu":true,
  "hideClueColumns":false,"wordLengthsEnabled":false,"multiPlayEnabled":
  false,"mediaPreviewEnabled":false,"mediaPreviewAndTextEnabled":true,
  "replay":false,"startButtonEnabled":false,"submitEnabled":false,
  "gatherEmail":false,"gatherMobile":false,"gatherName":false,"locale":
  "en-US","puzzleType":"CROSSWORD","layoutDiscoveredCommits":0,
  "layoutDiscoveredMillis":0,"w":15,"h":15,"box":[["\u0000","S","P","I",
      "N","E","T","S","\u0000","S","C","H","U","S","S"],["E","C","O","N",
      "O","M","I","C","\u0000","H","O","O","P","L","E"],["T","I","R","A",
      "M","I","S","U","\u0000","A","I","R","S","E","A"],["H","A","T","T",
      "E","R","\u0000","S","P","Y","N","O","V","E","L"],["A","T","E","I",
      "N","\u0000","L","E","E","S","\u0000","W","A","V","E"],["N","I","N",
      "E","\u0000","L","A","M","P","\u0000","F","I","N","E","D"],["O","C",
      "D","\u0000","F","I","V","E","S","P","O","T","\u0000","\u0000",
      "\u0000"],["L","A","S","A","L","L","E","\u0000","Q","U","I","Z","N",
      "O","S"],["\u0000","\u0000","\u0000","R","E","I","N","J","U","R","E",
      "\u0000","A","N","A"],["A","F","F","I","X","\u0000","D","U","A","L",
      "\u0000","C","U","E","D"],["I","R","A","S","\u0000","B","E","N","D",
      "\u0000","E","A","S","E","D"],["M","I","N","T","M","A","R","K",
      "\u0000","U","N","R","E","A","L"],["L","E","G","I","O","N","\u0000",
      "B","A","S","E","F","A","R","E"],["O","D","E","D","O","N","\u0000",
      "O","P","E","R","A","T","E","D"],["W","A","D","E","R","S","\u0000",
      "X","E","R","O","X","E","D","\u0000"]],"clueNums":[[0,14,16,18,21,24,
      27,30,0,39,44,47,50,53,55],[1,0,0,0,0,0,0,0,0,40,0,0,0,0,0],[2,0,0,0,
      0,0,0,0,0,41,0,0,0,0,0],[3,0,0,0,0,0,0,31,36,0,0,0,0,0,0],[4,0,0,0,0,
      0,28,0,0,0,0,48,0,0,0],[5,0,0,0,0,25,0,0,0,0,45,0,0,0,0],[6,0,0,0,22,
      0,0,0,0,42,0,0,0,0,0],[7,0,0,19,0,0,0,0,37,0,0,0,51,54,56],[0,0,0,20,
      0,0,0,32,0,0,0,0,52,0,0],[8,15,17,0,0,0,29,0,0,0,0,49,0,0,0],[9,0,0,
      0,0,26,0,0,0,0,46,0,0,0,0],[10,0,0,0,23,0,0,0,0,43,0,0,0,0,0],[11,0,
      0,0,0,0,0,33,38,0,0,0,0,0,0],[12,0,0,0,0,0,0,34,0,0,0,0,0,0,0],[13,0,
      0,0,0,0,0,35,0,0,0,0,0,0,0]],"boxToPlacedWordsIdxs":[[null,[2,47],[4,
        47],[6,47],[8,47],[11,47],[14,47],[16,47],null,[20,59],[23,59],[26,
        59],[28,59],[30,59],[32,59]],[[0,34],[2,34],[4,34],[6,34],[8,34],[
        11,34],[14,34],[16,34],null,[60,20],[23,60],[26,60],[28,60],[30,60],[
        32,60]],[[35,0],[2,35],[4,35],[6,35],[8,35],[11,35],[14,35],[16,35],
      null,[61,20],[23,61],[26,61],[28,61],[30,61],[32,61]],[[36,0],[2,36],[
        4,36],[6,36],[8,36],[11,36],null,[54,16],[18,54],[20,54],[23,54],[
        26,54],[28,54],[30,54],[32,54]],[[37,0],[2,37],[4,37],[6,37],[8,37],
      null,[15,52],[16,52],[18,52],[20,52],null,[65,26],[28,65],[30,65],[
        32,65]],[[38,0],[2,38],[4,38],[6,38],null,[12,50],[15,50],[16,50],[
        18,50],null,[24,63],[26,63],[28,63],[30,63],[32,63]],[[39,0],[2,39],[
        4,39],null,[9,49],[12,49],[15,49],[16,49],[18,49],[21,49],[24,49],[
        26,49],null,null,null],[[40,0],[2,40],[4,40],[7,40],[9,40],[12,40],[
        15,40],null,[58,18],[21,58],[24,58],[26,58],[29,58],[31,58],[33,58]],
    [null,null,null,[48,7],[9,48],[12,48],[15,48],[17,48],[18,48],[21,48],[
        24,48],null,[67,29],[31,67],[33,67]],[[1,41],[3,41],[5,41],[7,41],[
        9,41],null,[53,15],[17,53],[18,53],[21,53],null,[27,66],[29,66],[
        31,66],[33,66]],[[42,1],[3,42],[5,42],[7,42],null,[13,51],[15,51],[
        17,51],[18,51],null,[25,64],[27,64],[29,64],[31,64],[33,64]],[[43,
        1],[3,43],[5,43],[7,43],[10,43],[13,43],[15,43],[17,43],null,[22,
        62],[25,62],[27,62],[29,62],[31,62],[33,62]],[[44,1],[3,44],[5,44],[
        7,44],[10,44],[13,44],null,[55,17],[19,55],[22,55],[25,55],[27,55],[
        29,55],[31,55],[33,55]],[[45,1],[3,45],[5,45],[7,45],[10,45],[13,
        45],null,[56,17],[19,56],[22,56],[25,56],[27,56],[29,56],[31,56],[
        33,56]],[[46,1],[3,46],[5,46],[7,46],[10,46],[13,46],null,[57,17],[
        19,57],[22,57],[25,57],[27,57],[29,57],[31,57],null]],"placedWords":[
    {"originalTerm":"ETHANOL","nBoxes":7,"x":1,"y":0,"acrossNotDown":true,
      "clueNum":1,"clue":{"date":0,"clue":
        "The punch in Planter\u0027s Punch","fullSentenceLowerCase":""},
      "wordLens":[7],"intersects":false},{"originalTerm":"AIMLOW","nBoxes":
      6,"x":9,"y":0,"acrossNotDown":true,"clueNum":8,"clue":{"date":0,"clue":
        "Set overly easy goals","fullSentenceLowerCase":""},"wordLens":[6],
      "intersects":false},{"originalTerm":"SCIATICA","nBoxes":8,"x":0,"y":
      1,"acrossNotDown":true,"clueNum":14,"clue":{"date":0,"clue":
        "Disk problem","fullSentenceLowerCase":""},"wordLens":[8],
      "intersects":false},{"originalTerm":"FRIEDA","nBoxes":6,"x":9,"y":1,
      "acrossNotDown":true,"clueNum":15,"clue":{"date":0,"clue":
        "Curly-haired \"Peanuts\" character","fullSentenceLowerCase":""},
      "wordLens":[6],"intersects":false},{"originalTerm":"PORTENDS","nBoxes":
      8,"x":0,"y":2,"acrossNotDown":true,"clueNum":16,"clue":{"date":0,
        "clue":"Foreshadows","fullSentenceLowerCase":""},"wordLens":[8],
      "intersects":false},{"originalTerm":"FANGED","nBoxes":6,"x":9,"y":2,
      "acrossNotDown":true,"clueNum":17,"clue":{"date":0,"clue":
        "Like rattlers","fullSentenceLowerCase":""},"wordLens":[6],
      "intersects":false},{"originalTerm":"INATIE","nBoxes":6,"x":0,"y":3,
      "acrossNotDown":true,"clueNum":18,"clue":{"date":0,"clue":"Drawn",
        "fullSentenceLowerCase":""},"wordLens":[6],"intersects":false},{
      "originalTerm":"ARISTIDE","nBoxes":8,"x":7,"y":3,"acrossNotDown":
      true,"clueNum":19,"clue":{"date":0,"clue":"Former Haitian president",
        "fullSentenceLowerCase":""},"wordLens":[8],"intersects":false},{
      "originalTerm":"NOMEN","nBoxes":5,"x":0,"y":4,"acrossNotDown":true,
      "clueNum":21,"clue":{"date":0,"clue":"Policy at certain clubs",
        "fullSentenceLowerCase":""},"wordLens":[5],"intersects":false},{
      "originalTerm":"FLEX","nBoxes":4,"x":6,"y":4,"acrossNotDown":true,
      "clueNum":22,"clue":{"date":0,"clue":"Display some guns",
        "fullSentenceLowerCase":""},"wordLens":[4],"intersects":false},{
      "originalTerm":"MOOR","nBoxes":4,"x":11,"y":4,"acrossNotDown":true,
      "clueNum":23,"clue":{"date":0,"clue":"\"Wuthering Heights\" setting",
        "fullSentenceLowerCase":""},"wordLens":[4],"intersects":false},{
      "originalTerm":"EMIR","nBoxes":4,"x":0,"y":5,"acrossNotDown":true,
      "clueNum":24,"clue":{"date":0,"clue":"Gulf States leader",
        "fullSentenceLowerCase":""},"wordLens":[4],"intersects":false},{
      "originalTerm":"LILI","nBoxes":4,"x":5,"y":5,"acrossNotDown":true,
      "clueNum":25,"clue":{"date":0,"clue":"Taylor of \"American Crime\"",
        "fullSentenceLowerCase":""},"wordLens":[4],"intersects":false},{
      "originalTerm":"BANNS","nBoxes":5,"x":10,"y":5,"acrossNotDown":true,
      "clueNum":26,"clue":{"date":0,"clue":"Wedding announcement",
        "fullSentenceLowerCase":""},"wordLens":[5],"intersects":false},{
      "originalTerm":"TIS","nBoxes":3,"x":0,"y":6,"acrossNotDown":true,
      "clueNum":27,"clue":{"date":0,"clue":"It\u0027s in many poems",
        "fullSentenceLowerCase":""},"wordLens":[3],"intersects":false},{
      "originalTerm":"LAVENDER","nBoxes":8,"x":4,"y":6,"acrossNotDown":
      true,"clueNum":28,"clue":{"date":0,"clue":"Sachet filler",
        "fullSentenceLowerCase":""},"wordLens":[8],"intersects":false},{
      "originalTerm":"SCUSEME","nBoxes":7,"x":0,"y":7,"acrossNotDown":true,
      "clueNum":30,"clue":{"date":0,"clue":"Informal passing remark?",
        "fullSentenceLowerCase":""},"wordLens":[7],"intersects":false},{
      "originalTerm":"JUNKBOX","nBoxes":7,"x":8,"y":7,"acrossNotDown":true,
      "clueNum":32,"clue":{"date":0,"clue":
        "Repository for spare or unused parts","fullSentenceLowerCase":""},
      "wordLens":[7],"intersects":false},{"originalTerm":"PEPSQUAD","nBoxes":
      8,"x":3,"y":8,"acrossNotDown":true,"clueNum":36,"clue":{"date":0,
        "clue":"Cheerleading outfit?","fullSentenceLowerCase":""},"wordLens":
      [8],"intersects":false},{"originalTerm":"APE","nBoxes":3,"x":12,"y":
      8,"acrossNotDown":true,"clueNum":38,"clue":{"date":0,"clue":"Lummox",
        "fullSentenceLowerCase":""},"wordLens":[3],"intersects":false},{
      "originalTerm":"SHAYS","nBoxes":5,"x":0,"y":9,"acrossNotDown":true,
      "clueNum":39,"clue":{"date":0,"clue":"Covered carriages",
        "fullSentenceLowerCase":""},"wordLens":[5],"intersects":false},{
      "originalTerm":"PURL","nBoxes":4,"x":6,"y":9,"acrossNotDown":true,
      "clueNum":42,"clue":{"date":0,"clue":"Reverse of a knit",
        "fullSentenceLowerCase":""},"wordLens":[4],"intersects":false},{
      "originalTerm":"USER","nBoxes":4,"x":11,"y":9,"acrossNotDown":true,
      "clueNum":43,"clue":{"date":0,"clue":"Selfish sort",
        "fullSentenceLowerCase":""},"wordLens":[4],"intersects":false},{
      "originalTerm":"COIN","nBoxes":4,"x":0,"y":10,"acrossNotDown":true,
      "clueNum":44,"clue":{"date":0,"clue":"Be the first to say",
        "fullSentenceLowerCase":""},"wordLens":[4],"intersects":false},{
      "originalTerm":"FOIE","nBoxes":4,"x":5,"y":10,"acrossNotDown":true,
      "clueNum":45,"clue":{"date":0,"clue":"Pâté base",
        "fullSentenceLowerCase":""},"wordLens":[4],"intersects":false},{
      "originalTerm":"ENERO","nBoxes":5,"x":10,"y":10,"acrossNotDown":true,
      "clueNum":46,"clue":{"date":0,"clue":"Month after diciembre",
        "fullSentenceLowerCase":""},"wordLens":[5],"intersects":false},{
      "originalTerm":"HOROWITZ","nBoxes":8,"x":0,"y":11,"acrossNotDown":
      true,"clueNum":47,"clue":{"date":0,"clue":
        "Immortal Kiev-born pianist","fullSentenceLowerCase":""},"wordLens":[
        8],"intersects":false},{"originalTerm":"CARFAX","nBoxes":6,"x":9,"y":
      11,"acrossNotDown":true,"clueNum":49,"clue":{"date":0,"clue":
        "Company whose name appears in an odometer in its logo",
        "fullSentenceLowerCase":""},"wordLens":[6],"intersects":false},{
      "originalTerm":"UPSVAN","nBoxes":6,"x":0,"y":12,"acrossNotDown":true,
      "clueNum":50,"clue":{"date":0,"clue":"Commonly seen brown vehicle",
        "fullSentenceLowerCase":""},"wordLens":[6],"intersects":false},{
      "originalTerm":"NAUSEATE","nBoxes":8,"x":7,"y":12,"acrossNotDown":
      true,"clueNum":51,"clue":{"date":0,"clue":"Gross out",
        "fullSentenceLowerCase":""},"wordLens":[8],"intersects":false},{
      "originalTerm":"SLEEVE","nBoxes":6,"x":0,"y":13,"acrossNotDown":true,
      "clueNum":53,"clue":{"date":0,"clue":"It may be rolled up on a farm",
        "fullSentenceLowerCase":""},"wordLens":[6],"intersects":false},{
      "originalTerm":"ONEEARED","nBoxes":8,"x":7,"y":13,"acrossNotDown":
      true,"clueNum":54,"clue":{"date":0,"clue":"Like the praying mantis",
        "fullSentenceLowerCase":""},"wordLens":[8],"intersects":false},{
      "originalTerm":"SEALED","nBoxes":6,"x":0,"y":14,"acrossNotDown":true,
      "clueNum":55,"clue":{"date":0,"clue":"In Tupperware, say",
        "fullSentenceLowerCase":""},"wordLens":[6],"intersects":false},{
      "originalTerm":"SADDLED","nBoxes":7,"x":7,"y":14,"acrossNotDown":
      true,"clueNum":56,"clue":{"date":0,"clue":"Ready to ride",
        "fullSentenceLowerCase":""},"wordLens":[7],"intersects":false},{
      "originalTerm":"ECONOMIC","nBoxes":8,"x":1,"y":0,"acrossNotDown":
      false,"clueNum":1,"clue":{"date":0,"clue":"Cost-effective",
        "fullSentenceLowerCase":""},"wordLens":[8],"intersects":false},{
      "originalTerm":"TIRAMISU","nBoxes":8,"x":2,"y":0,"acrossNotDown":
      false,"clueNum":2,"clue":{"date":0,"clue":"Dessert with a kick",
        "fullSentenceLowerCase":""},"wordLens":[8],"intersects":false},{
      "originalTerm":"HATTER","nBoxes":6,"x":3,"y":0,"acrossNotDown":false,
      "clueNum":3,"clue":{"date":0,"clue":"Mad __","fullSentenceLowerCase":
        ""},"wordLens":[6],"intersects":false},{"originalTerm":"ATEIN",
      "nBoxes":5,"x":4,"y":0,"acrossNotDown":false,"clueNum":4,"clue":{
        "date":0,"clue":"Took courses at home","fullSentenceLowerCase":""},
      "wordLens":[5],"intersects":false},{"originalTerm":"NINE","nBoxes":4,
      "x":5,"y":0,"acrossNotDown":false,"clueNum":5,"clue":{"date":0,"clue":
        "West Coast ZIP starter","fullSentenceLowerCase":""},"wordLens":[4],
      "intersects":false},{"originalTerm":"OCD","nBoxes":3,"x":6,"y":0,
      "acrossNotDown":false,"clueNum":6,"clue":{"date":0,"clue":
        "Neatnik\u0027s possible condition, briefly","fullSentenceLowerCase":
        ""},"wordLens":[3],"intersects":false},{"originalTerm":"LASALLE",
      "nBoxes":7,"x":7,"y":0,"acrossNotDown":false,"clueNum":7,"clue":{
        "date":0,"clue":"Mississippi explorer","fullSentenceLowerCase":""},
      "wordLens":[7],"intersects":false},{"originalTerm":"AFFIX","nBoxes":
      5,"x":9,"y":0,"acrossNotDown":false,"clueNum":8,"clue":{"date":0,
        "clue":"Tack on","fullSentenceLowerCase":""},"wordLens":[5],
      "intersects":false},{"originalTerm":"IRAS","nBoxes":4,"x":10,"y":0,
      "acrossNotDown":false,"clueNum":9,"clue":{"date":0,"clue":
        "Line 32 items on 1040 forms","fullSentenceLowerCase":""},"wordLens":
      [4],"intersects":false},{"originalTerm":"MINTMARK","nBoxes":8,"x":11,
      "y":0,"acrossNotDown":false,"clueNum":10,"clue":{"date":0,"clue":
        "D, P or S, on quarters","fullSentenceLowerCase":""},"wordLens":[8],
      "intersects":false},{"originalTerm":"LEGION","nBoxes":6,"x":12,"y":0,
      "acrossNotDown":false,"clueNum":11,"clue":{"date":0,"clue":
        "Vast multitude","fullSentenceLowerCase":""},"wordLens":[6],
      "intersects":false},{"originalTerm":"ODEDON","nBoxes":6,"x":13,"y":0,
      "acrossNotDown":false,"clueNum":12,"clue":{"date":0,"clue":
        "Had way too much of","fullSentenceLowerCase":""},"wordLens":[6],
      "intersects":false},{"originalTerm":"WADERS","nBoxes":6,"x":14,"y":0,
      "acrossNotDown":false,"clueNum":13,"clue":{"date":0,"clue":
        "Angler\u0027s gear","fullSentenceLowerCase":""},"wordLens":[6],
      "intersects":false},{"originalTerm":"SPINETS","nBoxes":7,"x":0,"y":1,
      "acrossNotDown":false,"clueNum":14,"clue":{"date":0,"clue":
        "Grand children?","fullSentenceLowerCase":""},"wordLens":[7],
      "intersects":false},{"originalTerm":"REINJURE","nBoxes":8,"x":8,"y":
      3,"acrossNotDown":false,"clueNum":20,"clue":{"date":0,"clue":
        "Pull over, say?","fullSentenceLowerCase":""},"wordLens":[8],
      "intersects":false},{"originalTerm":"FIVESPOT","nBoxes":8,"x":6,"y":
      4,"acrossNotDown":false,"clueNum":22,"clue":{"date":0,"clue":"Fin",
        "fullSentenceLowerCase":""},"wordLens":[8],"intersects":false},{
      "originalTerm":"LAMP","nBoxes":4,"x":5,"y":5,"acrossNotDown":false,
      "clueNum":25,"clue":{"date":0,"clue":"Lighter","fullSentenceLowerCase":
        ""},"wordLens":[4],"intersects":false},{"originalTerm":"BEND",
      "nBoxes":4,"x":10,"y":5,"acrossNotDown":false,"clueNum":26,"clue":{
        "date":0,"clue":"Give a little","fullSentenceLowerCase":""},
      "wordLens":[4],"intersects":false},{"originalTerm":"LEES","nBoxes":4,
      "x":4,"y":6,"acrossNotDown":false,"clueNum":28,"clue":{"date":0,"clue":
        "Wranglers alternative","fullSentenceLowerCase":""},"wordLens":[4],
      "intersects":false},{"originalTerm":"DUAL","nBoxes":4,"x":9,"y":6,
      "acrossNotDown":false,"clueNum":29,"clue":{"date":0,"clue":
        "Part of DINK","fullSentenceLowerCase":""},"wordLens":[4],
      "intersects":false},{"originalTerm":"SPYNOVEL","nBoxes":8,"x":3,"y":
      7,"acrossNotDown":false,"clueNum":31,"clue":{"date":0,"clue":
        "Fleming work","fullSentenceLowerCase":""},"wordLens":[8],
      "intersects":false},{"originalTerm":"BASEFARE","nBoxes":8,"x":12,"y":
      7,"acrossNotDown":false,"clueNum":33,"clue":{"date":0,"clue":
        "Ride cost before taxes and such","fullSentenceLowerCase":""},
      "wordLens":[8],"intersects":false},{"originalTerm":"OPERATED","nBoxes":
      8,"x":13,"y":7,"acrossNotDown":false,"clueNum":34,"clue":{"date":0,
        "clue":"Ran","fullSentenceLowerCase":""},"wordLens":[8],"intersects":
      false},{"originalTerm":"XEROXED","nBoxes":7,"x":14,"y":7,
      "acrossNotDown":false,"clueNum":35,"clue":{"date":0,"clue":"Ran off",
        "fullSentenceLowerCase":""},"wordLens":[7],"intersects":false},{
      "originalTerm":"QUIZNOS","nBoxes":7,"x":7,"y":8,"acrossNotDown":
      false,"clueNum":37,"clue":{"date":0,"clue":"Subway alternative",
        "fullSentenceLowerCase":""},"wordLens":[7],"intersects":false},{
      "originalTerm":"SCHUSS","nBoxes":6,"x":0,"y":9,"acrossNotDown":false,
      "clueNum":39,"clue":{"date":0,"clue":"Speed down a slope",
        "fullSentenceLowerCase":""},"wordLens":[6],"intersects":false},{
      "originalTerm":"HOOPLE","nBoxes":6,"x":1,"y":9,"acrossNotDown":false,
      "clueNum":40,"clue":{"date":0,"clue":"Rockers Mott the __",
        "fullSentenceLowerCase":""},"wordLens":[6],"intersects":false},{
      "originalTerm":"AIRSEA","nBoxes":6,"x":2,"y":9,"acrossNotDown":false,
      "clueNum":41,"clue":{"date":0,"clue":"Like some offshore rescues",
        "fullSentenceLowerCase":""},"wordLens":[6],"intersects":false},{
      "originalTerm":"UNREAL","nBoxes":6,"x":11,"y":9,"acrossNotDown":
      false,"clueNum":43,"clue":{"date":0,"clue":
        "\"Are you kidding me?!\"","fullSentenceLowerCase":""},"wordLens":[
        6],"intersects":false},{"originalTerm":"FINED","nBoxes":5,"x":5,"y":
      10,"acrossNotDown":false,"clueNum":45,"clue":{"date":0,"clue":
        "Punished in court, in a way","fullSentenceLowerCase":""},"wordLens":
      [5],"intersects":false},{"originalTerm":"EASED","nBoxes":5,"x":10,"y":
      10,"acrossNotDown":false,"clueNum":46,"clue":{"date":0,"clue":
        "Let up","fullSentenceLowerCase":""},"wordLens":[5],"intersects":
      false},{"originalTerm":"WAVE","nBoxes":4,"x":4,"y":11,"acrossNotDown":
      false,"clueNum":48,"clue":{"date":0,"clue":"Parade greeting",
        "fullSentenceLowerCase":""},"wordLens":[4],"intersects":false},{
      "originalTerm":"CUED","nBoxes":4,"x":9,"y":11,"acrossNotDown":false,
      "clueNum":49,"clue":{"date":0,"clue":"Helped on stage",
        "fullSentenceLowerCase":""},"wordLens":[4],"intersects":false},{
      "originalTerm":"ANA","nBoxes":3,"x":8,"y":12,"acrossNotDown":false,
      "clueNum":52,"clue":{"date":0,"clue":"Literary assortment",
        "fullSentenceLowerCase":""},"wordLens":[3],"intersects":false}],
  "tags":["tca"],"backgroundShapeBoxes":[],"level":0,"levelsExhausted":
  true,"haveMessages":true,"placeAll":false,"caseSensitive":false}

